{"uuids": {"phone_id": "d5d171d3-ba02-402d-a1dc-ee1ef4736d3f", "uuid": "c870780c-6e42-4e64-88f8-a1cb60395951", "client_session_id": "86995180-9252-42fe-97aa-2ef1ba1f6638", "advertising_id": "18769ebd-dbaf-47e4-a404-5e7cd1a1a6e0", "android_device_id": "android-69c7c7adb09525fc", "request_id": "3ceb383b-c4d4-4475-bc38-de8300cfbf05", "tray_session_id": "a0690da5-9fe6-42a7-8247-430e6bb33dd1"}, "mid": "YxokeAABAAFlf6I_1XcJy5-DRN6J", "ig_u_rur": null, "ig_www_claim": null, "authorization_data": {"ds_user_id": "37816144422", "sessionid": "37816144422%3AkS1B4EUcGscA8w%3A4%3AAYepGBk2B1Gkur9aIY1SxOjxe8Vp0nHVHs6QgP5CvA"}, "cookies": {}, "last_login": 1662657665.9996722, "device_settings": {"app_version": "203.0.0.29.118", "android_version": 26, "android_release": "8.0.0", "dpi": "480dpi", "resolution": "1080x1920", "manufacturer": "Xiaomi", "device": "capricorn", "model": "MI 5s", "cpu": "qcom", "version_code": "314665256"}, "user_agent": "Instagram 203.0.0.29.118 Android (26/8.0.0; 480dpi; 1080x1920; Xiaomi; MI 5s; capricorn; qcom; en_GB; 314665256)", "country": "GB", "country_code": 44, "locale": "en_GB", "timezone_offset": 3600}